{
    "group_whitelist": {
        "description": "群聊白名单",
        "hint": "仅在白名单里的群启用本插件功能，不填表示所有群都启用",
        "type": "list",
        "default": []
    },
    "notify_on_success": {
        "description": "成功时发送通知",
        "hint": "开启后，文件检查有效时也会发送一条回复通知。关闭则只在文件失效时通知。",
        "type": "bool",
        "default": true
    },
    "pre_check_delay_seconds": {
        "description": "预检延时 (秒)",
        "hint": "收到文件后，等待多少秒再开始进行阶段一的即时检查。建议设为3-10秒。",
        "type": "int",
        "default": 10
    },
    "check_delay_seconds": {
        "description": "复核间隔时间 (秒)",
        "hint": "预检通过后，再等待多少秒进行时效性复核。",
        "type": "int",
        "default": 300
    },
    "preview_length": {
        "description": "文本预览长度 (字符)",
        "hint": "设置在回复中显示的文本内容预览的最大字符数。",
        "type": "int",
        "default": 200
    },
    "forward_threshold": {
        "description": "长消息合并转发阈值 (字符)",
        "hint": "当插件的单条回复（主要是带预览的）超过此字数时，将自动转为合并转发。设置为 0 则禁用此功能。",
        "type": "int",
        "default": 300
    }
}
